versallm/__init__.py
versallm/llms/anthropic_client.py
versallm/llms/base.py
versallm/llms/groq_client.py
versallm/llms/openai_client.py
versallm/utils/memory.py
versallm/utils/response.py
versallm/utils/types.py
versallm-0.1.1.dist-info/LICENSE
versallm-0.1.1.dist-info/METADATA
versallm-0.1.1.dist-info/WHEEL
versallm-0.1.1.dist-info/RECORD
