Metadata-Version: 2.1
Name: versallm
Version: 0.1.1
Summary: VersaLLM is a versatile language model client that supports multiple backend models including OpenAI, Anthropic, and Groq. It provides a unified interface for interacting with these models and includes tools for executing functions based on user prompts.
Author: Mohwit
Author-email: mohwits@gmail.com
Requires-Python: >=3.10,<4.0
Classifier: Programming Language :: Python :: 3
Classifier: Programming Language :: Python :: 3.10
Classifier: Programming Language :: Python :: 3.11
Classifier: Programming Language :: Python :: 3.12
Requires-Dist: anthropic (>=0.31.0,<0.32.0)
Requires-Dist: groq (>=0.9.0,<0.10.0)
Requires-Dist: openai (>=1.35.13,<2.0.0)
